CHANGES.rst
CONTRIBUTORS.rst
MANIFEST.in
README.rst
setup.py
src/collective/__init__.py
src/collective.searchform.egg-info/PKG-INFO
src/collective.searchform.egg-info/SOURCES.txt
src/collective.searchform.egg-info/dependency_links.txt
src/collective.searchform.egg-info/entry_points.txt
src/collective.searchform.egg-info/namespace_packages.txt
src/collective.searchform.egg-info/not-zip-safe
src/collective.searchform.egg-info/requires.txt
src/collective.searchform.egg-info/top_level.txt
src/collective/searchform/__init__.py
src/collective/searchform/configure.zcml
src/collective/searchform/search.py
src/collective/searchform/search_form.pt
src/collective/searchform/tests.py