Metadata-Version: 1.0
Name: collective.searchform
Version: 1.0
Summary: An extended search form for Plone >= 4.2
Home-page: https://github.com/collective/collective.searchform
Author: Tom Gross
Author-email: itconsense@gmail.com
License: gpl
Platform: UNKNOWN
Classifier: Programming Language :: Python
Classifier: Framework :: Plone
Classifier: Framework :: Plone :: 4.2
Classifier: Framework :: Plone :: 4.3
